sammo/__init__.py
sammo/base.py
sammo/base_test.py
sammo/compactbars.py
sammo/compactbars_test.py
sammo/components.py
sammo/components_test.py
sammo/css_matching.py
sammo/css_matching_test.py
sammo/data.py
sammo/data_tests.py
sammo/dataformatters.py
sammo/dataformatters_test.py
sammo/express.py
sammo/express_test.py
sammo/extractors.py
sammo/extractors_test.py
sammo/instructions.py
sammo/instructions_test.py
sammo/integration_test.py
sammo/mutators.py
sammo/mutators_test.py
sammo/runners.py
sammo/runners_test.py
sammo/scheduler.py
sammo/search.py
sammo/search_op.py
sammo/search_op_test.py
sammo/store.py
sammo/store_test.py
sammo/throttler.py
sammo/throttler_test.py
sammo/utils.py
sammo-0.3.3.dist-info/LICENSE
sammo-0.3.3.dist-info/METADATA
sammo-0.3.3.dist-info/WHEEL
sammo-0.3.3.dist-info/RECORD
