Metadata-Version: 2.3
Name: sammo
Version: 0.3.3
Summary: A flexible, easy-to-use library for running and optimizing prompts for Large Language Models (LLMs).
License: MIT
Author: Tobias Schnabel
Requires-Python: >=3.9,<3.13
Classifier: License :: OSI Approved :: MIT License
Classifier: Programming Language :: Python :: 3
Classifier: Programming Language :: Python :: 3.9
Classifier: Programming Language :: Python :: 3.10
Classifier: Programming Language :: Python :: 3.11
Classifier: Programming Language :: Python :: 3.12
Provides-Extra: parser
Requires-Dist: PyYAML (>=6.0,<7.0)
Requires-Dist: aiohttp (>=3.6,<4.0)
Requires-Dist: async-timeout (>=4.0.3,<5.0.0)
Requires-Dist: beartype (>=0.15,<0.16)
Requires-Dist: benepar (>=0.2,<0.3) ; extra == "parser"
Requires-Dist: cssselect (>=1.2,<2.0)
Requires-Dist: dill (>=0.3,<0.4)
Requires-Dist: diskcache (>=5.2,<6.0)
Requires-Dist: filelock (>=3.12,<4.0)
Requires-Dist: frozendict (>=2.3,<3.0)
Requires-Dist: jsonpath_ng (>=1.5,<2.0)
Requires-Dist: lxml (>=5.3,<6.0)
Requires-Dist: markdown-it-py (>=2.2,<3.0)
Requires-Dist: mistletoe (>=1.4,<2.0)
Requires-Dist: more-itertools (>=10.1,<11.0)
Requires-Dist: numpy (>=1.25,<2.0)
Requires-Dist: orjson (>=3.9,<4.0)
Requires-Dist: pybars3 (>=0.9,<0.10)
Requires-Dist: pyglove (>=0.4,<0.5)
Requires-Dist: quattro (>=24,<25)
Requires-Dist: spacy (>=3.6,<4.0)
Requires-Dist: tabulate (>=0.9,<0.10)
Requires-Dist: xmltodict (>=0.13,<0.14)
Project-URL: Documentation, https://microsoft.github.io/sammo/docs/
Project-URL: Repository, https://github.com/microsoft/sammo/
